countries.py
countries_capital.py
get_name_gender_religion.py
get_random_people.py
names.py
qualifications.py
utils.py
get_random_people-1.1.3.dist-info/LICENSE
get_random_people-1.1.3.dist-info/METADATA
get_random_people-1.1.3.dist-info/WHEEL
get_random_people-1.1.3.dist-info/top_level.txt
get_random_people-1.1.3.dist-info/RECORD
