Metadata-Version: 2.1
Name: get-random-people
Version: 1.1.3
Summary: Generates random information of a person
Home-page: https://github.com/internetwebsoftwares/get_random_people.git
Author: Ata Shaikh, Nicholes Viktor, InternetWebSoftwares
Author-email: atasteven49@gmail.com
Keywords: random,fake,dataset,user data,fake data,user information,python,generate data,generate fake data,users
Classifier: Programming Language :: Python :: 3
Classifier: License :: OSI Approved :: MIT License
Classifier: Operating System :: OS Independent
Requires-Python: >=3.6
License-File: LICENSE
